weatherflow4py/__init__.py
weatherflow4py/api.py
weatherflow4py/const.py
weatherflow4py/exceptions.py
weatherflow4py/models/__init__.py
weatherflow4py/models/rest/__init__.py
weatherflow4py/models/rest/device.py
weatherflow4py/models/rest/forecast.py
weatherflow4py/models/rest/observation.py
weatherflow4py/models/rest/stations.py
weatherflow4py/models/rest/status.py
weatherflow4py/models/rest/unified.py
weatherflow4py/models/ws/__init__.py
weatherflow4py/models/ws/custom_types.py
weatherflow4py/models/ws/obs.py
weatherflow4py/models/ws/types.py
weatherflow4py/models/ws/websocket_request.py
weatherflow4py/models/ws/websocket_response.py
weatherflow4py/ws.py
weatherflow4py-1.4.1.dist-info/LICENSE
weatherflow4py-1.4.1.dist-info/METADATA
weatherflow4py-1.4.1.dist-info/WHEEL
weatherflow4py-1.4.1.dist-info/RECORD
